sosaxy/__init__.py
sosaxy/command_line.py
sosaxy/record_stream.py
sosaxy/utils.py
sosaxy-0.4.0.dist-info/DESCRIPTION.rst
sosaxy-0.4.0.dist-info/METADATA
sosaxy-0.4.0.dist-info/RECORD
sosaxy-0.4.0.dist-info/WHEEL
sosaxy-0.4.0.dist-info/entry_points.txt
sosaxy-0.4.0.dist-info/metadata.json
sosaxy-0.4.0.dist-info/top_level.txt
